Workbook

Sheet Dashboard
A1: Plumas Waterway Testing — Public Transparency Ledger
A2: Live summary. All figures pull automatically from the Donations, Expenses, and Hours tabs.
A4: Money in & out
A5: Gross donations received | B5: =SUM(Donations!C2:C1000) -> 2650
A6: Platform & processing fees | B6: =SUM(Donations!D2:D1000) -> 4.95
A7: Net donations (kept) | B7: =SUM(Donations!E2:E1000) -> 2645.05
A8: Total spent (all expenses) | B8: =SUM(Expenses!D2:D1000) -> 1155
A9: Cash on hand | B9: =B7-B8 -> 1490.05
A11: Spending by purpose
A12: Bucket | B12: Spent | C12: % of spend
A13: Operations (incl. billed hours) | B13: =SUMIF(Expenses!C2:C1000,"Operations",Expenses!D2:D1000) -> 625 | C13: =IF($B$8=0,0,B13/$B$8) -> 0.54112554
A14: Testing (labs, supplies, contractors) | B14: =SUMIF(Expenses!C2:C1000,"Testing",Expenses!D2:D1000) -> 480 | C14: =IF($B$8=0,0,B14/$B$8) -> 0.41558442
A15: Admin (fees, filings, insurance) | B15: =SUMIF(Expenses!C2:C1000,"Admin",Expenses!D2:D1000) -> 50 | C15: =IF($B$8=0,0,B15/$B$8) -> 0.043290043
A16: Total | B16: =SUM(B13:B15) -> 1155
A18: Donations by type
A19: Type | B19: Net received
A20: Unrestricted | B20: =SUMIF(Donations!F2:F1000,"Unrestricted",Donations!E2:E1000) -> 145.05
A21: Restricted to testing | B21: =SUMIF(Donations!F2:F1000,"Restricted-Testing",Donations!E2:E1000) -> 2500
A24: Labor transparency
A25: Total hours logged | B25: =SUM(Hours!E2:E1000) -> 16.5
A26: Total $ value of logged hours | B26: =SUM(Hours!G2:G1000) -> 625
A27: Blended hourly rate | B27: =IF(B25=0,0,B26/B25) -> 37.878788
A29: Note: logged hours show labor contributed. Cash actually paid for that labor appears in Expenses (bucket = Operations), so totals are not double-counted.

Sheet Donations
A1: Donations In
A2: Record every gift. Net = Gross - Fees. Sample rows are shaded — overwrite or delete them.
A4: Date | B4: Donor / source | C4: Gross amount | D4: Fees | E4: Net | F4: Type | G4: Platform | H4: Notes
A5: 2026-07-01 | B5: Online donor (J. Rivera) | C5: 100 | D5: 3.2 | E5: =C5-D5 -> 96.8 | F5: Unrestricted | G5: Givebutter | H5: Tips on; donor covered fees
A6: 2026-07-03 | B6: Community fund grant | C6: 2500 | D6: 0 | E6: =C6-D6 -> 2500 | F6: Restricted-Testing | G6: Check | H6: For Q3 lab fees
A7: 2026-07-05 | B7: Anonymous | C7: 50 | D7: 1.75 | E7: =C7-D7 -> 48.25 | F7: Unrestricted | G7: Donorbox
E8: =IF(C8="","",C8-D8)
E9: =IF(C9="","",C9-D9)
E10: =IF(C10="","",C10-D10)
E11: =IF(C11="","",C11-D11)
E12: =IF(C12="","",C12-D12)
E13: =IF(C13="","",C13-D13)
E14: =IF(C14="","",C14-D14)
E15: =IF(C15="","",C15-D15)
E16: =IF(C16="","",C16-D16)
E17: =IF(C17="","",C17-D17)
E18: =IF(C18="","",C18-D18)
E19: =IF(C19="","",C19-D19)
... E47: =IF(C47="","",C47-D47)

Sheet Expenses
A1: Expenses Out
A2: Every dollar spent, tagged by purpose. Paying someone for logged hours? Use bucket = Operations.
A4: Date | B4: Payee / description | C4: Bucket | D4: Amount | E4: Paid via | F4: Linked to (person/invoice) | G4: Notes
A5: 2026-07-10 | B5: R. Vukich — map dev & data (12.5 hrs) | C5: Operations | D5: 625 | E5: Bank transfer | F5: Hours tab, wk 27 | G5: Approved rate $50/hr
A6: 2026-07-15 | B6: NorCal Analytical Lab — glyphosate panel | C6: Testing | D6: 480 | E6: Card | F6: Invoice #1042 | G6: 3 sites
A7: 2026-07-15 | B7: Givebutter fees (covered) | C7: Admin | D7: 0 | E7: Auto
A8: 2026-07-20 | B8: CA AG registration (CT-1) | C8: Admin | D8: 50 | E8: Card

Sheet Hours
A1: Hours Log
A2: Transparent record of time spent. $ value = Hours × Rate (auto). This documents labor; cash paid shows in Expenses.
A4: Date | B4: Person | C4: Task / description | D4: Role | E4: Hours | F4: Rate ($/hr) | G4: $ value | H4: Approved by
A5: 2026-07-08 | B5: R. Vukich | C5: Build donate feature + map updates | D5: Tech/Operations | E5: 6.5 | F5: 50 | G5: =E5*F5 -> 325 | H5: Board 6/30
A6: 2026-07-09 | B6: R. Vukich | C6: Data scrape + QA of application records | D6: Data | E6: 6 | F6: 50 | G6: =E6*F6 -> 300 | H6: Board 6/30
A7: 2026-07-12 | B7: Volunteer (M. Lee) | C7: Water sampling, 3 sites | D7: Field/Testing | E7: 4 | F7: 0 | G7: =E7*F7 -> 0 | H7: Board 6/30
G8: =IF(E8="","",E8*F8)
G9: =IF(E9="","",E9*F9)
G10: =IF(E10="","",E10*F10)
G11: =IF(E11="","",E11*F11)
G12: =IF(E12="","",E12*F12)
G13: =IF(E13="","",E13*F13)
G14: =IF(E14="","",E14*F14)
G15: =IF(E15="","",E15*F15)
G16: =IF(E16="","",E16*F16)
G17: =IF(E17="","",E17*F17)
G18: =IF(E18="","",E18*F18)
G19: =IF(E19="","",E19*F19)
... G47: =IF(E47="","",E47*F47)

Sheet How to use
A1: How to use this ledger
A2: A plain-language guide. Keep this tab public alongside the others.
A5: Purpose | B5: This ledger is the org's public promise of transparency: every dollar in, every dollar out, and every hour billed, visible to anyone.
A6: 1. Log donations | B6: On the Donations tab, add each gift: gross amount, fees, and whether it was unrestricted or restricted to testing. Net is calculated for you.
A7: 2. Log expenses | B7: On the Expenses tab, record each payment and tag its Bucket: Operations (includes paying people for logged hours), Testing, or Admin.
A8: 3. Log hours | B8: On the Hours tab, record who worked, on what, for how long, at what board-approved rate. The $ value calculates automatically.
A9: 4. Read the Dashboard | B9: Everything rolls up on the Dashboard: money in/out, cash on hand, spend by purpose, and labor contributed. Nothing to update there.
A10: Avoid double-counting | B10: Logged hours show labor contributed. The actual cash paid for that labor is entered once, in Expenses, under the Operations bucket.
A11: Restricted funds | B11: If a donor says 'for testing,' mark it Restricted-Testing and make sure testing spending is at least that amount. The Dashboard shows both.
A12: Publishing | B12: Share a read-only copy (Google Sheets 'view only', a PDF export, or an embedded view) on the website. Update monthly.
A13: Good governance | B13: Have the board approve hourly rates in advance and record the approval date in the 'Approved by' column. Paid people should recuse from voting on their own pay.
A14: Not legal/tax advice | B14: This template supports transparency but isn't a substitute for a bookkeeper or CPA at tax time.
